{
    "num_iteration": 4297,
    "root_position": [
        100,
        70,
        80
    ],
    "user_list": [
        {
            "id": 0,
            "position": [
                69,
                96
            ],
            "time_start": 146,
            "tw_size": 4,
            "datarate": 53,
            "total_data": 10,
            "max_data": 999999
        },
        {
            "id": 1,
            "position": [
                25,
                17
            ],
            "time_start": 71,
            "tw_size": 6,
            "datarate": 39,
            "total_data": 10,
            "max_data": 999999
        },
        {
            "id": 2,
            "position": [
                21,
                124
            ],
            "time_start": 163,
            "tw_size": 7,
            "datarate": 38,
            "total_data": 10,
            "max_data": 999999
        },
        {
            "id": 3,
            "position": [
                93,
                183
            ],
            "time_start": 62,
            "tw_size": 5,
            "datarate": 35,
            "total_data": 10,
            "max_data": 999999
        },
        {
            "id": 4,
            "position": [
                144,
                2
            ],
            "time_start": 173,
            "tw_size": 3,
            "datarate": 52,
            "total_data": 10,
            "max_data": 999999
        },
        {
            "id": 5,
            "position": [
                167,
                185
            ],
            "time_start": 12,
            "tw_size": 4,
            "datarate": 43,
            "total_data": 10,
            "max_data": 999999
        },
        {
            "id": 6,
            "position": [
                65,
                40
            ],
            "time_start": 4,
            "tw_size": 5,
            "datarate": 53,
            "total_data": 10,
            "max_data": 999999
        },
        {
            "id": 7,
            "position": [
                61,
                155
            ],
            "time_start": 57,
            "tw_size": 3,
            "datarate": 43,
            "total_data": 10,
            "max_data": 999999
        },
        {
            "id": 8,
            "position": [
                75,
                125
            ],
            "time_start": 19,
            "tw_size": 7,
            "datarate": 57,
            "total_data": 10,
            "max_data": 999999
        },
        {
            "id": 9,
            "position": [
                189,
                97
            ],
            "time_start": 178,
            "tw_size": 7,
            "datarate": 43,
            "total_data": 10,
            "max_data": 999999
        },
        {
            "id": 10,
            "position": [
                107,
                116
            ],
            "time_start": 72,
            "tw_size": 6,
            "datarate": 53,
            "total_data": 10,
            "max_data": 999999
        },
        {
            "id": 11,
            "position": [
                169,
                143
            ],
            "time_start": 67,
            "tw_size": 6,
            "datarate": 57,
            "total_data": 10,
            "max_data": 999999
        },
        {
            "id": 12,
            "position": [
                172,
                8
            ],
            "time_start": 18,
            "tw_size": 7,
            "datarate": 54,
            "total_data": 10,
            "max_data": 999999
        },
        {
            "id": 13,
            "position": [
                62,
                28
            ],
            "time_start": 5,
            "tw_size": 5,
            "datarate": 53,
            "total_data": 10,
            "max_data": 999999
        },
        {
            "id": 14,
            "position": [
                178,
                166
            ],
            "time_start": 113,
            "tw_size": 7,
            "datarate": 56,
            "total_data": 10,
            "max_data": 999999
        },
        {
            "id": 15,
            "position": [
                90,
                86
            ],
            "time_start": 101,
            "tw_size": 7,
            "datarate": 40,
            "total_data": 10,
            "max_data": 999999
        },
        {
            "id": 16,
            "position": [
                39,
                196
            ],
            "time_start": 8,
            "tw_size": 5,
            "datarate": 37,
            "total_data": 10,
            "max_data": 999999
        },
        {
            "id": 17,
            "position": [
                107,
                163
            ],
            "time_start": 94,
            "tw_size": 6,
            "datarate": 47,
            "total_data": 10,
            "max_data": 999999
        },
        {
            "id": 18,
            "position": [
                33,
                85
            ],
            "time_start": 122,
            "tw_size": 5,
            "datarate": 45,
            "total_data": 10,
            "max_data": 999999
        },
        {
            "id": 19,
            "position": [
                43,
                132
            ],
            "time_start": 152,
            "tw_size": 5,
            "datarate": 55,
            "total_data": 10,
            "max_data": 999999
        },
        {
            "id": 20,
            "position": [
                148,
                30
            ],
            "time_start": 12,
            "tw_size": 5,
            "datarate": 60,
            "total_data": 10,
            "max_data": 999999
        },
        {
            "id": 21,
            "position": [
                65,
                58
            ],
            "time_start": 97,
            "tw_size": 4,
            "datarate": 46,
            "total_data": 10,
            "max_data": 999999
        },
        {
            "id": 22,
            "position": [
                79,
                157
            ],
            "time_start": 188,
            "tw_size": 3,
            "datarate": 48,
            "total_data": 10,
            "max_data": 999999
        },
        {
            "id": 23,
            "position": [
                31,
                119
            ],
            "time_start": 71,
            "tw_size": 6,
            "datarate": 42,
            "total_data": 10,
            "max_data": 999999
        },
        {
            "id": 24,
            "position": [
                193,
                167
            ],
            "time_start": 170,
            "tw_size": 6,
            "datarate": 52,
            "total_data": 10,
            "max_data": 999999
        },
        {
            "id": 25,
            "position": [
                95,
                51
            ],
            "time_start": 47,
            "tw_size": 7,
            "datarate": 53,
            "total_data": 10,
            "max_data": 999999
        },
        {
            "id": 26,
            "position": [
                75,
                28
            ],
            "time_start": 119,
            "tw_size": 7,
            "datarate": 38,
            "total_data": 10,
            "max_data": 999999
        },
        {
            "id": 27,
            "position": [
                186,
                140
            ],
            "time_start": 190,
            "tw_size": 6,
            "datarate": 51,
            "total_data": 10,
            "max_data": 999999
        },
        {
            "id": 28,
            "position": [
                39,
                135
            ],
            "time_start": 10,
            "tw_size": 5,
            "datarate": 51,
            "total_data": 10,
            "max_data": 999999
        },
        {
            "id": 29,
            "position": [
                42,
                101
            ],
            "time_start": 59,
            "tw_size": 4,
            "datarate": 39,
            "total_data": 10,
            "max_data": 999999
        },
        {
            "id": 30,
            "position": [
                82,
                63
            ],
            "time_start": 109,
            "tw_size": 6,
            "datarate": 56,
            "total_data": 10,
            "max_data": 999999
        },
        {
            "id": 31,
            "position": [
                153,
                124
            ],
            "time_start": 21,
            "tw_size": 6,
            "datarate": 38,
            "total_data": 10,
            "max_data": 999999
        },
        {
            "id": 32,
            "position": [
                17,
                55
            ],
            "time_start": 175,
            "tw_size": 7,
            "datarate": 45,
            "total_data": 10,
            "max_data": 999999
        },
        {
            "id": 33,
            "position": [
                89,
                10
            ],
            "time_start": 71,
            "tw_size": 4,
            "datarate": 49,
            "total_data": 10,
            "max_data": 999999
        },
        {
            "id": 34,
            "position": [
                0,
                169
            ],
            "time_start": 16,
            "tw_size": 4,
            "datarate": 48,
            "total_data": 10,
            "max_data": 999999
        },
        {
            "id": 35,
            "position": [
                177,
                181
            ],
            "time_start": 16,
            "tw_size": 5,
            "datarate": 41,
            "total_data": 10,
            "max_data": 999999
        },
        {
            "id": 36,
            "position": [
                132,
                164
            ],
            "time_start": 118,
            "tw_size": 7,
            "datarate": 55,
            "total_data": 10,
            "max_data": 999999
        },
        {
            "id": 37,
            "position": [
                13,
                122
            ],
            "time_start": 94,
            "tw_size": 4,
            "datarate": 50,
            "total_data": 10,
            "max_data": 999999
        },
        {
            "id": 38,
            "position": [
                68,
                141
            ],
            "time_start": 103,
            "tw_size": 3,
            "datarate": 45,
            "total_data": 10,
            "max_data": 999999
        },
        {
            "id": 39,
            "position": [
                141,
                150
            ],
            "time_start": 157,
            "tw_size": 7,
            "datarate": 36,
            "total_data": 10,
            "max_data": 999999
        },
        {
            "id": 40,
            "position": [
                143,
                187
            ],
            "time_start": 176,
            "tw_size": 5,
            "datarate": 38,
            "total_data": 10,
            "max_data": 999999
        },
        {
            "id": 41,
            "position": [
                136,
                150
            ],
            "time_start": 67,
            "tw_size": 5,
            "datarate": 49,
            "total_data": 10,
            "max_data": 999999
        },
        {
            "id": 42,
            "position": [
                149,
                84
            ],
            "time_start": 142,
            "tw_size": 7,
            "datarate": 59,
            "total_data": 10,
            "max_data": 999999
        },
        {
            "id": 43,
            "position": [
                189,
                88
            ],
            "time_start": 58,
            "tw_size": 5,
            "datarate": 50,
            "total_data": 10,
            "max_data": 999999
        },
        {
            "id": 44,
            "position": [
                5,
                128
            ],
            "time_start": 70,
            "tw_size": 3,
            "datarate": 45,
            "total_data": 10,
            "max_data": 999999
        },
        {
            "id": 45,
            "position": [
                116,
                45
            ],
            "time_start": 35,
            "tw_size": 7,
            "datarate": 39,
            "total_data": 10,
            "max_data": 999999
        },
        {
            "id": 46,
            "position": [
                8,
                156
            ],
            "time_start": 69,
            "tw_size": 6,
            "datarate": 37,
            "total_data": 10,
            "max_data": 999999
        },
        {
            "id": 47,
            "position": [
                61,
                146
            ],
            "time_start": 70,
            "tw_size": 6,
            "datarate": 51,
            "total_data": 10,
            "max_data": 999999
        },
        {
            "id": 48,
            "position": [
                151,
                123
            ],
            "time_start": 34,
            "tw_size": 6,
            "datarate": 52,
            "total_data": 10,
            "max_data": 999999
        },
        {
            "id": 49,
            "position": [
                86,
                106
            ],
            "time_start": 26,
            "tw_size": 4,
            "datarate": 54,
            "total_data": 10,
            "max_data": 999999
        },
        {
            "id": 50,
            "position": [
                132,
                99
            ],
            "time_start": 164,
            "tw_size": 3,
            "datarate": 48,
            "total_data": 10,
            "max_data": 999999
        },
        {
            "id": 51,
            "position": [
                23,
                159
            ],
            "time_start": 15,
            "tw_size": 3,
            "datarate": 44,
            "total_data": 10,
            "max_data": 999999
        },
        {
            "id": 52,
            "position": [
                143,
                92
            ],
            "time_start": 139,
            "tw_size": 4,
            "datarate": 52,
            "total_data": 10,
            "max_data": 999999
        },
        {
            "id": 53,
            "position": [
                4,
                55
            ],
            "time_start": 173,
            "tw_size": 6,
            "datarate": 44,
            "total_data": 10,
            "max_data": 999999
        },
        {
            "id": 54,
            "position": [
                61,
                70
            ],
            "time_start": 56,
            "tw_size": 7,
            "datarate": 36,
            "total_data": 10,
            "max_data": 999999
        },
        {
            "id": 55,
            "position": [
                153,
                34
            ],
            "time_start": 108,
            "tw_size": 4,
            "datarate": 52,
            "total_data": 10,
            "max_data": 999999
        },
        {
            "id": 56,
            "position": [
                71,
                116
            ],
            "time_start": 44,
            "tw_size": 7,
            "datarate": 46,
            "total_data": 10,
            "max_data": 999999
        },
        {
            "id": 57,
            "position": [
                161,
                80
            ],
            "time_start": 165,
            "tw_size": 4,
            "datarate": 45,
            "total_data": 10,
            "max_data": 999999
        },
        {
            "id": 58,
            "position": [
                88,
                112
            ],
            "time_start": 122,
            "tw_size": 5,
            "datarate": 58,
            "total_data": 10,
            "max_data": 999999
        },
        {
            "id": 59,
            "position": [
                103,
                172
            ],
            "time_start": 63,
            "tw_size": 4,
            "datarate": 48,
            "total_data": 10,
            "max_data": 999999
        },
        {
            "id": 60,
            "position": [
                48,
                176
            ],
            "time_start": 76,
            "tw_size": 4,
            "datarate": 51,
            "total_data": 10,
            "max_data": 999999
        },
        {
            "id": 61,
            "position": [
                200,
                109
            ],
            "time_start": 161,
            "tw_size": 6,
            "datarate": 59,
            "total_data": 10,
            "max_data": 999999
        },
        {
            "id": 62,
            "position": [
                65,
                160
            ],
            "time_start": 181,
            "tw_size": 6,
            "datarate": 47,
            "total_data": 10,
            "max_data": 999999
        },
        {
            "id": 63,
            "position": [
                149,
                103
            ],
            "time_start": 194,
            "tw_size": 5,
            "datarate": 44,
            "total_data": 10,
            "max_data": 999999
        },
        {
            "id": 64,
            "position": [
                110,
                181
            ],
            "time_start": 5,
            "tw_size": 4,
            "datarate": 59,
            "total_data": 10,
            "max_data": 999999
        },
        {
            "id": 65,
            "position": [
                45,
                38
            ],
            "time_start": 185,
            "tw_size": 5,
            "datarate": 43,
            "total_data": 10,
            "max_data": 999999
        },
        {
            "id": 66,
            "position": [
                39,
                68
            ],
            "time_start": 135,
            "tw_size": 4,
            "datarate": 35,
            "total_data": 10,
            "max_data": 999999
        },
        {
            "id": 67,
            "position": [
                186,
                118
            ],
            "time_start": 166,
            "tw_size": 7,
            "datarate": 52,
            "total_data": 10,
            "max_data": 999999
        },
        {
            "id": 68,
            "position": [
                144,
                79
            ],
            "time_start": 138,
            "tw_size": 4,
            "datarate": 51,
            "total_data": 10,
            "max_data": 999999
        },
        {
            "id": 69,
            "position": [
                97,
                69
            ],
            "time_start": 160,
            "tw_size": 7,
            "datarate": 44,
            "total_data": 10,
            "max_data": 999999
        },
        {
            "id": 70,
            "position": [
                96,
                186
            ],
            "time_start": 18,
            "tw_size": 6,
            "datarate": 51,
            "total_data": 10,
            "max_data": 999999
        },
        {
            "id": 71,
            "position": [
                77,
                189
            ],
            "time_start": 126,
            "tw_size": 6,
            "datarate": 60,
            "total_data": 10,
            "max_data": 999999
        },
        {
            "id": 72,
            "position": [
                52,
                86
            ],
            "time_start": 182,
            "tw_size": 4,
            "datarate": 45,
            "total_data": 10,
            "max_data": 999999
        },
        {
            "id": 73,
            "position": [
                179,
                6
            ],
            "time_start": 32,
            "tw_size": 3,
            "datarate": 58,
            "total_data": 10,
            "max_data": 999999
        },
        {
            "id": 74,
            "position": [
                94,
                76
            ],
            "time_start": 160,
            "tw_size": 6,
            "datarate": 54,
            "total_data": 10,
            "max_data": 999999
        },
        {
            "id": 75,
            "position": [
                126,
                117
            ],
            "time_start": 18,
            "tw_size": 7,
            "datarate": 60,
            "total_data": 10,
            "max_data": 999999
        },
        {
            "id": 76,
            "position": [
                4,
                16
            ],
            "time_start": 32,
            "tw_size": 5,
            "datarate": 54,
            "total_data": 10,
            "max_data": 999999
        },
        {
            "id": 77,
            "position": [
                100,
                82
            ],
            "time_start": 20,
            "tw_size": 4,
            "datarate": 53,
            "total_data": 10,
            "max_data": 999999
        },
        {
            "id": 78,
            "position": [
                61,
                2
            ],
            "time_start": 137,
            "tw_size": 5,
            "datarate": 39,
            "total_data": 10,
            "max_data": 999999
        },
        {
            "id": 79,
            "position": [
                95,
                42
            ],
            "time_start": 184,
            "tw_size": 4,
            "datarate": 45,
            "total_data": 10,
            "max_data": 999999
        }
    ]
}